filterbox/__init__.py
filterbox/api.md
filterbox/btree.py
filterbox/concurrent/__init__.py
filterbox/concurrent/how_it_works.md
filterbox/concurrent/main.py
filterbox/constants.py
filterbox/exceptions.py
filterbox/frozen/__init__.py
filterbox/frozen/frozen_attr.py
filterbox/frozen/how_it_works.md
filterbox/frozen/main.py
filterbox/frozen/utils.py
filterbox/init_helpers.py
filterbox/mutable/__init__.py
filterbox/mutable/how_it_works.md
filterbox/mutable/main.py
filterbox/mutable/mutable_attr.py
filterbox/perf.py
filterbox/pickling.py
filterbox/utils.py
filterbox-1.0.0.dist-info/LICENSE
filterbox-1.0.0.dist-info/WHEEL
filterbox-1.0.0.dist-info/METADATA
filterbox-1.0.0.dist-info/RECORD
